nwbwidgets/__init__.py
nwbwidgets/allen.py
nwbwidgets/base.py
nwbwidgets/behavior.py
nwbwidgets/brains.py
nwbwidgets/dynamictablesummary.py
nwbwidgets/ecephys.py
nwbwidgets/ephys_viz_interface.py
nwbwidgets/file.py
nwbwidgets/icephys.py
nwbwidgets/image.py
nwbwidgets/misc.py
nwbwidgets/ophys.py
nwbwidgets/panel.py
nwbwidgets/spectrum.py
nwbwidgets/timeseries.py
nwbwidgets/version.py
nwbwidgets/view.py
nwbwidgets/analysis/__init__.py
nwbwidgets/analysis/spikes.py
nwbwidgets/controllers/__init__.py
nwbwidgets/controllers/group_and_sort_controllers.py
nwbwidgets/controllers/misc.py
nwbwidgets/controllers/time_window_controllers.py
nwbwidgets/utils/__init__.py
nwbwidgets/utils/cmaps.py
nwbwidgets/utils/dandi.py
nwbwidgets/utils/dependencies.py
nwbwidgets/utils/dynamictable.py
nwbwidgets/utils/functional.py
nwbwidgets/utils/mpl.py
nwbwidgets/utils/plotly.py
nwbwidgets/utils/pynwb.py
nwbwidgets/utils/testing.py
nwbwidgets/utils/timeseries.py
nwbwidgets/utils/units.py
nwbwidgets/utils/widgets.py
nwbwidgets-0.11.3.dist-info/LICENSE
nwbwidgets-0.11.3.dist-info/METADATA
nwbwidgets-0.11.3.dist-info/WHEEL
nwbwidgets-0.11.3.dist-info/top_level.txt
nwbwidgets-0.11.3.dist-info/RECORD
