Metadata-Version: 2.1
Name: nwbwidgets
Version: 0.11.3
Summary: This is nwbwidgets, widgets for viewing the contents of a NWB-file in Jupyter Notebooks using ipywidgets.
Home-page: https://github.com/NeurodataWithoutBorders/nwb-jupyter-widgets
Author: Ben Dichter
Author-email: ben.dichter@catalystneuro.com
License: BSD
Keywords: jupyter,hdf5,notebook,nwb
Platform: UNKNOWN
Classifier: Operating System :: OS Independent
Classifier: Development Status :: 3 - Alpha
Classifier: Framework :: Jupyter
Classifier: License :: OSI Approved :: MIT License
Classifier: Programming Language :: Python :: 3.7
Classifier: Programming Language :: Python :: 3.8
Classifier: Programming Language :: Python :: 3.9
Requires-Python: >=3.7
Requires-Dist: numpy
Requires-Dist: matplotlib
Requires-Dist: scikit-image
Requires-Dist: pynwb
Requires-Dist: ipympl
Requires-Dist: ipydatagrid
Requires-Dist: ipyvolume (>=0.6.0a10)
Requires-Dist: ipywidgets (>=8.0.0)
Requires-Dist: plotly (==5.13.1)
Requires-Dist: tqdm (>=4.36.0)
Requires-Dist: zarr
Requires-Dist: tifffile
Requires-Dist: ndx-spectrum
Requires-Dist: ndx-icephys-meta
Requires-Dist: ndx-grayscalevolume
Requires-Dist: trimesh
Requires-Dist: dandi (>=0.55.0)
Requires-Dist: importlib-metadata (<5.0)
Requires-Dist: fsspec
Requires-Dist: requests
Requires-Dist: aiohttp
Requires-Dist: ipydatawidgets (==4.3.2)
Requires-Dist: ipyfilechooser (==0.6.0)
Provides-Extra: full
Requires-Dist: ccfwidget ; extra == 'full'
Requires-Dist: aiohttp ; extra == 'full'
Requires-Dist: nilearn ; extra == 'full'
Requires-Dist: trimesh ; extra == 'full'
Provides-Extra: human_electrodes
Requires-Dist: nilearn ; extra == 'human_electrodes'
Requires-Dist: trimesh ; extra == 'human_electrodes'
Provides-Extra: mouse_electrodes
Requires-Dist: ccfwidget ; extra == 'mouse_electrodes'
Requires-Dist: aiohttp ; extra == 'mouse_electrodes'
